ripple_ws_client/ws_client.py
ripple_websocket_client-1.0.2.dist-info/LICENSE
ripple_websocket_client-1.0.2.dist-info/METADATA
ripple_websocket_client-1.0.2.dist-info/WHEEL
ripple_websocket_client-1.0.2.dist-info/top_level.txt
ripple_websocket_client-1.0.2.dist-info/RECORD
