Metadata-Version: 2.1
Name: ripple-websocket-client
Version: 1.0.2
Summary: websocket client connect and message use mqtt
Home-page: UNKNOWN
Author: Zhenyu Han
Author-email: hanzy@rippleinfo.com
License: UNKNOWN
Platform: UNKNOWN
Classifier: Programming Language :: Python :: 3
Classifier: License :: OSI Approved :: MIT License
Classifier: Operating System :: OS Independent
Requires-Python: >=3.0.*
Requires-Dist: websocket-client (==0.57.0)
Requires-Dist: pyjwt (==1.7.1)
Requires-Dist: mqtt-codec (==1.0.2)
